{
  "environment": "web",
  "format": "html",
  "prefix": "https://storage.googleapis.com",
  "mainga": "UA-49880327-14",
  "updated": "2024-07-22T12:24:26Z",
  "id": "how-to-add-a-client-action",
  "duration": 9,
  "title": "How to Add a Client Action",
  "authors": "Tati, Dan",
  "summary": "How to Add a Client Action",
  "source": "how-to-add-a-client-action.md",
  "theme": "",
  "status": [
    "draft"
  ],
  "category": [
    "grr"
  ],
  "tags": [
    "action",
    "client",
    "grr"
  ],
  "feedback": "https://github.com/google/grr/issues",
  "url": "how-to-add-a-client-action"
}
